openshift_release/__init__.py
openshift_release/api_client.py
openshift_release/configuration.py
openshift_release/exceptions.py
openshift_release/rest.py
openshift_release/api/__init__.py
openshift_release/api/apis_api.py
openshift_release/api/art_openshift_io_api.py
openshift_release/api/art_openshift_io_v1alpha1_api.py
openshift_release/api/version_api.py
openshift_release/models/__init__.py
openshift_release/models/com_github_vfreex_release_apiserver_pkg_apis_art_v1alpha1_advisory.py
openshift_release/models/com_github_vfreex_release_apiserver_pkg_apis_art_v1alpha1_advisory_list.py
openshift_release/models/com_github_vfreex_release_apiserver_pkg_apis_art_v1alpha1_advisory_spec.py
openshift_release/models/com_github_vfreex_release_apiserver_pkg_apis_art_v1alpha1_advisory_status.py
openshift_release/models/com_github_vfreex_release_apiserver_pkg_apis_art_v1alpha1_brew_build.py
openshift_release/models/com_github_vfreex_release_apiserver_pkg_apis_art_v1alpha1_build.py
openshift_release/models/com_github_vfreex_release_apiserver_pkg_apis_art_v1alpha1_build_jenkins_info.py
openshift_release/models/com_github_vfreex_release_apiserver_pkg_apis_art_v1alpha1_build_list.py
openshift_release/models/com_github_vfreex_release_apiserver_pkg_apis_art_v1alpha1_build_spec.py
openshift_release/models/com_github_vfreex_release_apiserver_pkg_apis_art_v1alpha1_component.py
openshift_release/models/com_github_vfreex_release_apiserver_pkg_apis_art_v1alpha1_component_dist_git.py
openshift_release/models/com_github_vfreex_release_apiserver_pkg_apis_art_v1alpha1_component_git_source.py
openshift_release/models/com_github_vfreex_release_apiserver_pkg_apis_art_v1alpha1_component_image.py
openshift_release/models/com_github_vfreex_release_apiserver_pkg_apis_art_v1alpha1_component_list.py
openshift_release/models/com_github_vfreex_release_apiserver_pkg_apis_art_v1alpha1_component_source.py
openshift_release/models/com_github_vfreex_release_apiserver_pkg_apis_art_v1alpha1_component_spec.py
openshift_release-0.0.2.dist-info/METADATA
openshift_release-0.0.2.dist-info/WHEEL
openshift_release-0.0.2.dist-info/top_level.txt
openshift_release-0.0.2.dist-info/RECORD
